radmxtk/__init__.py
radmxtk/pyrads_gui.py
radmxtk/examples/exampleVoxel.yaml
radmxtk/examples/pyrads_gui_demo.py
radmxtk/pyrads_gui/__init__.py
radmxtk/pyrads_gui/controller.py
radmxtk/pyrads_gui/models.py
radmxtk/pyrads_gui/views.py
radmxtk-0.0.1.dist-info/LICENSE
radmxtk-0.0.1.dist-info/METADATA
radmxtk-0.0.1.dist-info/WHEEL
radmxtk-0.0.1.dist-info/top_level.txt
radmxtk-0.0.1.dist-info/RECORD
